Metadata-Version: 2.1
Name: prozect
Version: 0.0
Summary: Gauss
Author-email: kaludjamoskovia@gmail.com
License: UNKNOWN
Platform: UNKNOWN
